datawords/__about__.py
datawords/__init__.py
datawords/_utils.py
datawords/constants.py
datawords/indexes.py
datawords/install_pytorch.py
datawords/models.py
datawords/parsers.py
datawords/py.typed
datawords/ranking.py
datawords/utils.py
datawords/deepnlp/__init__.py
datawords/deepnlp/core.py
datawords/deepnlp/translators.py
datawords/deepnlp/translators2.py
datawords/deepnlp/utils.py
datawords/files/stop_en.txt
datawords/files/stop_es.txt
datawords/files/stop_pt.txt
datawords-0.7.4.dist-info/METADATA
datawords-0.7.4.dist-info/WHEEL
datawords-0.7.4.dist-info/licenses/LICENSE
datawords-0.7.4.dist-info/licenses/NOTICE.md
datawords-0.7.4.dist-info/RECORD
