Metadata-Version: 2.1
Name: datawords
Version: 0.7.4
Summary: A library to work with text data
Project-URL: Documentation, https://github.com/unknown/datawords#readme
Project-URL: Issues, https://github.com/unknown/datawords/issues
Project-URL: Source, https://github.com/unknown/datawords
Author-email: Xavier Petit <nuxion@gmail.com>
License-Expression: MPL-2.0
License-File: LICENSE
License-File: NOTICE.md
Keywords: datascience,nlp,text,transformers
Classifier: Development Status :: 4 - Beta
Classifier: Intended Audience :: Developers
Classifier: Programming Language :: Python
Classifier: Programming Language :: Python :: 3.8
Classifier: Programming Language :: Python :: 3.9
Classifier: Programming Language :: Python :: 3.10
Classifier: Programming Language :: Python :: 3.11
Classifier: Programming Language :: Python :: Implementation :: CPython
Classifier: Programming Language :: Python :: Implementation :: PyPy
Classifier: Topic :: Scientific/Engineering :: Artificial Intelligence
Requires-Python: >=3.8
Requires-Dist: annoy~=1.17.0
Requires-Dist: attrs~=23.1.0
Requires-Dist: cattrs~=23.1.2
Requires-Dist: emoji~=1.5.0
Requires-Dist: gensim~=4.3.0
Requires-Dist: langcodes
Requires-Dist: langdetect~=1.0.9
Requires-Dist: language
Requires-Dist: nltk~=3.6.4
Requires-Dist: scikit-learn~=1.2.0
Requires-Dist: scikit-network~=0.28.3
Requires-Dist: spacy~=3.4.4
Requires-Dist: tqdm
Requires-Dist: unidecode~=1.3.2
Provides-Extra: transformers
Requires-Dist: sacremoses~=0.0.53; extra == 'transformers'
Requires-Dist: sentencepiece; extra == 'transformers'
Requires-Dist: toolz; extra == 'transformers'
Requires-Dist: transformers; extra == 'transformers'
